favicorn/__init__.py
favicorn/connection_manager.py
favicorn/reader.py
favicorn/server.py
favicorn/writer.py
favicorn/builders/__init__.py
favicorn/builders/asgi.py
favicorn/connections/__init__.py
favicorn/connections/tcp/__init__.py
favicorn/connections/tcp/connection.py
favicorn/controllers/__init__.py
favicorn/controllers/asgi/__init__.py
favicorn/controllers/asgi/controller.py
favicorn/controllers/asgi/event_manager.py
favicorn/controllers/asgi/factory.py
favicorn/controllers/asgi/responses.py
favicorn/controllers/asgi/scope_builder.py
favicorn/event_buses/__init__.py
favicorn/event_buses/deque.py
favicorn/i/__init__.py
favicorn/i/builder.py
favicorn/i/connection.py
favicorn/i/controller.py
favicorn/i/event_bus.py
favicorn/i/server.py
favicorn/i/socket_provider.py
favicorn/i/protocols/__init__.py
favicorn/i/protocols/http/__init__.py
favicorn/i/protocols/http/parser.py
favicorn/i/protocols/http/protocol.py
favicorn/i/protocols/http/request_metadata.py
favicorn/i/protocols/http/response_metadata.py
favicorn/i/protocols/http/serializer.py
favicorn/i/protocols/websocket/__init__.py
favicorn/i/protocols/websocket/parser.py
favicorn/i/protocols/websocket/protocol.py
favicorn/i/protocols/websocket/serializer.py
favicorn/protocols/__init__.py
favicorn/protocols/http/__init__.py
favicorn/protocols/http/parsers/__init__.py
favicorn/protocols/http/parsers/h11_parser/__init__.py
favicorn/protocols/http/parsers/h11_parser/parser.py
favicorn/protocols/http/parsers/httptools_parser/__init__.py
favicorn/protocols/http/parsers/httptools_parser/factory.py
favicorn/protocols/http/parsers/httptools_parser/parser.py
favicorn/protocols/http/serializers/__init__.py
favicorn/protocols/http/serializers/base.py
favicorn/protocols/websocket/__init__.py
favicorn/protocols/websocket/parsers/__init__.py
favicorn/protocols/websocket/parsers/wsproto_parser.py
favicorn/protocols/websocket/serializers/__init__.py
favicorn/protocols/websocket/serializers/wsproto_serializer.py
favicorn-0.0.5.dist-info/METADATA
favicorn-0.0.5.dist-info/WHEEL
favicorn-0.0.5.dist-info/top_level.txt
favicorn-0.0.5.dist-info/RECORD
