Metadata-Version: 2.1
Name: favicorn
Version: 0.0.5
Summary: ASGI webserver
Author: Vladimir Vojtenko
Author-email: vladimirdev635@gmail.com
License: MIT
